<Properties StartupConfiguration="{FB31A455-D843-494D-A2FF-51243F231538}|Default">
  <MonoDevelop.Ide.ItemProperties.05.06.00__SolvingAQuadraticEquasion PreferredExecutionTarget="MonoDevelop.Default" />
  <MonoDevelop.Ide.Workbench>
    <Pads>
      <Pad Id="ProjectPad">
        <State name="__root__">
          <Node name="05.06.00_SolvingAQuadraticEquasion" expanded="True" selected="True" />
        </State>
      </Pad>
    </Pads>
  </MonoDevelop.Ide.Workbench>
  <MonoDevelop.Ide.DebuggingService.PinnedWatches />
  <MonoDevelop.Ide.Workspace ActiveConfiguration="Release" />
  <MonoDevelop.Ide.DebuggingService.Breakpoints>
    <BreakpointStore />
  </MonoDevelop.Ide.DebuggingService.Breakpoints>
  <MultiItemStartupConfigurations />
</Properties>